{
	"CONTROL_FOREVER": "repete para sempre",
	"CONTROL_REPEAT": "repete %1 vezes",
	"CONTROL_IF": "se %1 , então",
	"CONTROL_ELSE": "senão,",
	"CONTROL_STOP": "pára",
	"CONTROL_STOP_ALL": "tudo",
	"CONTROL_STOP_THIS": "este guião",
	"CONTROL_STOP_OTHER": "os teus outros guiões",
	"CONTROL_WAIT": "espera %1 s",
	"CONTROL_WAITUNTIL": "espera até que %1",
	"CONTROL_REPEATUNTIL": "até que %1 , repete",
	"CONTROL_WHILE": "enquanto %1",
	"CONTROL_FOREACH": "para cada %1 em %2",
	"CONTROL_STARTASCLONE": "Quando fores criado como um clone",
	"CONTROL_CREATECLONEOF": "cria um clone de %1",
	"CONTROL_CREATECLONEOF_MYSELF": "ti mesmo",
	"CONTROL_DELETETHISCLONE": "remove-te como clone",
	"CONTROL_COUNTER": "contador",
	"CONTROL_INCRCOUNTER": "incrementa o contador",
	"CONTROL_CLEARCOUNTER": "põe o contador a zero",
	"CONTROL_ALLATONCE": "executa tudo de uma vez",
	"DATA_SETVARIABLETO": "altera %1 para %2",
	"DATA_CHANGEVARIABLEBY": "adiciona a %1 o valor %2",
	"DATA_SHOWVARIABLE": "mostra a variável %1",
	"DATA_HIDEVARIABLE": "esconde a variável %1",
	"DATA_ADDTOLIST": "acrescenta %1 a %2",
	"DATA_DELETEOFLIST": "remove %1 de %2",
	"DATA_DELETEALLOFLIST": "remove tudo de %1",
	"DATA_INSERTATLIST": "insere %1 como %2 de %3",
	"DATA_REPLACEITEMOFLIST": "substitui %1 de %2 por %3",
	"DATA_ITEMOFLIST": "%1 de %2",
	"DATA_ITEMNUMOFLIST": "o número do item %1 em %2",
	"DATA_LENGTHOFLIST": "o comprimento de %1",
	"DATA_LISTCONTAINSITEM": "%1 contém %2",
	"DATA_SHOWLIST": "mostra a lista %1",
	"DATA_HIDELIST": "esconde a lista %1",
	"DATA_INDEX_ALL": "tudo",
	"DATA_INDEX_LAST": "o último item",
	"DATA_INDEX_RANDOM": "um item ao acaso",
	"EVENT_WHENFLAGCLICKED": "Quando alguém clicar em %1",
	"EVENT_WHENTHISSPRITECLICKED": "Quando alguém clicar em ti",
	"EVENT_WHENSTAGECLICKED": "Quando alguém clicar no palco",
	"EVENT_WHENTOUCHINGOBJECT": "Quando tocares em %1",
	"EVENT_WHENBROADCASTRECEIVED": "Quando receberes a mensagem %1",
	"EVENT_WHENBACKDROPSWITCHESTO": "Quando o cenário mudar para %1",
	"EVENT_WHENGREATERTHAN": "Quando o valor do sensor %1 exceder %2",
	"EVENT_WHENGREATERTHAN_TIMER": "o valor do cronómetro",
	"EVENT_WHENGREATERTHAN_LOUDNESS": "o volume no microfone",
	"EVENT_BROADCAST": "difunde a mensagem %1",
	"EVENT_BROADCASTANDWAIT": "difunde a mensagem %1 e espera",
	"EVENT_WHENKEYPRESSED": "Quando alguém pressionar a tecla %1",
	"EVENT_WHENKEYPRESSED_SPACE": "espaço",
	"EVENT_WHENKEYPRESSED_LEFT": "seta para a esquerda",
	"EVENT_WHENKEYPRESSED_RIGHT": "seta para a direita",
	"EVENT_WHENKEYPRESSED_DOWN": "seta para baixo",
	"EVENT_WHENKEYPRESSED_UP": "seta para cima",
	"EVENT_WHENKEYPRESSED_ANY": "qualquer",
	"LOOKS_SAYFORSECS": "diz %1 durante %2 s",
	"LOOKS_SAY": "diz %1",
	"LOOKS_HELLO": "Olá!",
	"LOOKS_THINKFORSECS": "pensa %1 durante %2 s",
	"LOOKS_THINK": "pensa %1",
	"LOOKS_HMM": "Hmm…",
	"LOOKS_SHOW": "mostra-te",
	"LOOKS_HIDE": "esconde-te",
	"LOOKS_HIDEALLSPRITES": "esconde todos os actores",
	"LOOKS_EFFECT_COLOR": "cor",
	"LOOKS_EFFECT_FISHEYE": "olho de peixe",
	"LOOKS_EFFECT_WHIRL": "remoinho",
	"LOOKS_EFFECT_PIXELATE": "pixelização",
	"LOOKS_EFFECT_MOSAIC": "mosaico",
	"LOOKS_EFFECT_BRIGHTNESS": "brilho",
	"LOOKS_EFFECT_GHOST": "fantasma",
	"LOOKS_CHANGEEFFECTBY": "adiciona ao teu efeito %1 o valor %2",
	"LOOKS_SETEFFECTTO": "altera o teu efeito %1 para %2",
	"LOOKS_CLEARGRAPHICEFFECTS": "cancela os teus efeitos gráficos",
	"LOOKS_CHANGESIZEBY": "adiciona %1 ao teu tamanho",
	"LOOKS_SETSIZETO": "altera o teu tamanho para %1 %",
	"LOOKS_SIZE": "o tamanho",
	"LOOKS_CHANGESTRETCHBY": "adiciona %1 % ao esticamento",
	"LOOKS_SETSTRETCHTO": "altera o esticamento para %1 %",
	"LOOKS_SWITCHCOSTUMETO": "muda o teu traje para %1",
	"LOOKS_NEXTCOSTUME": "passa para o teu próximo traje",
	"LOOKS_SWITCHBACKDROPTO": "muda o cenário para %1",
	"LOOKS_GOTOFRONTBACK": "vai para a camada %1",
	"LOOKS_GOTOFRONTBACK_FRONT": "frontal",
	"LOOKS_GOTOFRONTBACK_BACK": "traseira",
	"LOOKS_GOFORWARDBACKWARDLAYERS": "%1 %2 camadas",
	"LOOKS_GOFORWARDBACKWARDLAYERS_FORWARD": "avança",
	"LOOKS_GOFORWARDBACKWARDLAYERS_BACKWARD": "recua",
	"LOOKS_BACKDROPNUMBERNAME": "%1 do cenário",
	"LOOKS_COSTUMENUMBERNAME": "%1 do traje",
	"LOOKS_NUMBERNAME_NUMBER": "o número",
	"LOOKS_NUMBERNAME_NAME": "o nome",
	"LOOKS_SWITCHBACKDROPTOANDWAIT": "muda o cenário para %1 e espera",
	"LOOKS_NEXTBACKDROP_BLOCK": "passa para o teu próximo cenário",
	"LOOKS_NEXTBACKDROP": "passa para o teu próximo cenário",
	"LOOKS_PREVIOUSBACKDROP": "o cenário anterior",
	"LOOKS_RANDOMBACKDROP": "um cenário ao acaso",
	"MOTION_MOVESTEPS": "anda %1 passos",
	"MOTION_TURNLEFT": "gira %1 %2 °",
	"MOTION_TURNRIGHT": "gira %1 %2 °",
	"MOTION_POINTINDIRECTION": "altera a tua direcção para %1 °",
	"MOTION_POINTTOWARDS": "aponta em direcção a %1",
	"MOTION_POINTTOWARDS_POINTER": "ponteiro do rato",
	"MOTION_POINTTOWARDS_RANDOM": "uma direcção ao acaso",
	"MOTION_GOTO": "vai para %1",
	"MOTION_GOTO_POINTER": "o ponteiro do rato",
	"MOTION_GOTO_RANDOM": "uma posição ao acaso",
	"MOTION_GOTOXY": "vai para a posição x: %1 y: %2",
	"MOTION_GLIDESECSTOXY": "desliza em %1 s para a posição x: %2 y: %3",
	"MOTION_GLIDETO": "desliza em %1 s em direcção a%2",
	"MOTION_GLIDETO_POINTER": "o ponteiro do rato",
	"MOTION_GLIDETO_RANDOM": "uma posição ao acaso",
	"MOTION_CHANGEXBY": "adiciona %1 ao teu x",
	"MOTION_SETX": "altera o teu x para %1",
	"MOTION_CHANGEYBY": "adiciona %1 ao teu y",
	"MOTION_SETY": "altera o teu y para %1",
	"MOTION_IFONEDGEBOUNCE": "se estiveres a bater na borda, ressalta",
	"MOTION_SETROTATIONSTYLE": "altera o teu estilo de rotação para %1",
	"MOTION_SETROTATIONSTYLE_LEFTRIGHT": "olha apenas para a esquerda e para a direita",
	"MOTION_SETROTATIONSTYLE_DONTROTATE": "não gires",
	"MOTION_SETROTATIONSTYLE_ALLAROUND": "gira a toda a volta",
	"MOTION_XPOSITION": "o x da tua posição",
	"MOTION_YPOSITION": "o y da tua posição",
	"MOTION_DIRECTION": "a direcção",
	"MOTION_SCROLLRIGHT": "rola %1 para a direita",
	"MOTION_SCROLLUP": "rola %1 para cima",
	"MOTION_ALIGNSCENE": "alinha a cena %1",
	"MOTION_ALIGNSCENE_BOTTOMLEFT": "ao fundo e à esquerda",
	"MOTION_ALIGNSCENE_BOTTOMRIGHT": "ao fundo e à direita",
	"MOTION_ALIGNSCENE_MIDDLE": "a meio",
	"MOTION_ALIGNSCENE_TOPLEFT": "no topo e à esquerda",
	"MOTION_ALIGNSCENE_TOPRIGHT": "no topo e à direita",
	"MOTION_XSCROLL": "o rolamento em x",
	"MOTION_YSCROLL": "o rolamento em y",
	"MOTION_STAGE_SELECTED": "Palco seleccionado: não tem blocos de movimento",
	"OPERATORS_ADD": "%1 + %2",
	"OPERATORS_SUBTRACT": "%1 − %2",
	"OPERATORS_MULTIPLY": "%1 × %2",
	"OPERATORS_DIVIDE": "%1 / %2",
	"OPERATORS_RANDOM": "um valor ao acaso entre %1 e %2",
	"OPERATORS_GT": "%1 > %2",
	"OPERATORS_LT": "%1 < %2",
	"OPERATORS_EQUALS": "%1 = %2",
	"OPERATORS_AND": "%1 e %2",
	"OPERATORS_OR": "%1 ou %2",
	"OPERATORS_NOT": "é falso que %1",
	"OPERATORS_JOIN": "a junção de %1 com %2",
	"OPERATORS_JOIN_APPLE": "maçã",
	"OPERATORS_JOIN_BANANA": "banana",
	"OPERATORS_LETTEROF": "o caractere %1 de %2",
	"OPERATORS_LETTEROF_APPLE": "a",
	"OPERATORS_LENGTH": "o comprimento de %1",
	"OPERATORS_CONTAINS": "%1 contém %2",
	"OPERATORS_MOD": "o resto de %1 a dividir por %2",
	"OPERATORS_ROUND": "o arredondamento de %1",
	"OPERATORS_MATHOP": "%1 de %2",
	"OPERATORS_MATHOP_ABS": "o valor absoluto",
	"OPERATORS_MATHOP_FLOOR": "o chão (o maior inteiro não superior)",
	"OPERATORS_MATHOP_CEILING": "o tecto (menor inteiro não inferior)",
	"OPERATORS_MATHOP_SQRT": "a raiz quadrada",
	"OPERATORS_MATHOP_SIN": "o seno",
	"OPERATORS_MATHOP_COS": "o cosseno",
	"OPERATORS_MATHOP_TAN": "a tangente",
	"OPERATORS_MATHOP_ASIN": "o arco-seno",
	"OPERATORS_MATHOP_ACOS": "o arco-cosseno",
	"OPERATORS_MATHOP_ATAN": "o arco-tangente",
	"OPERATORS_MATHOP_LN": "o logaritmo natural",
	"OPERATORS_MATHOP_LOG": "o logaritmo",
	"OPERATORS_MATHOP_EEXP": "a exponencial",
	"OPERATORS_MATHOP_10EXP": "10 ^",
	"PROCEDURES_DEFINITION": "Define %1",
	"SENSING_TOUCHINGOBJECT": "estás a tocar em %1",
	"SENSING_TOUCHINGOBJECT_POINTER": "o ponteiro do rato",
	"SENSING_TOUCHINGOBJECT_EDGE": "a borda",
	"SENSING_TOUCHINGCOLOR": "estás a tocar na cor %1",
	"SENSING_COLORISTOUCHINGCOLOR": "a cor %1 está a tocar na cor %2",
	"SENSING_DISTANCETO": "a distância até %1",
	"SENSING_DISTANCETO_POINTER": "o ponteiro do rato",
	"SENSING_ASKANDWAIT": "pergunta %1 e espera pela resposta",
	"SENSING_ASK_TEXT": "Como te chamas?",
	"SENSING_ANSWER": "a resposta",
	"SENSING_KEYPRESSED": "a tecla %1 está a ser pressionada",
	"SENSING_MOUSEDOWN": "o botão do rato está pressionado",
	"SENSING_MOUSEX": "o x da posição do rato",
	"SENSING_MOUSEY": "o y da posição do rato",
	"SENSING_SETDRAGMODE": "altera o teu modo de arrasto para %1",
	"SENSING_SETDRAGMODE_DRAGGABLE": "arrastável",
	"SENSING_SETDRAGMODE_NOTDRAGGABLE": "não arrastável",
	"SENSING_LOUDNESS": "o volume no microfone",
	"SENSING_LOUD": "o som é forte",
	"SENSING_TIMER": "o valor do cronómetro",
	"SENSING_RESETTIMER": "reinicia o cronómetro",
	"SENSING_OF": "%1 de %2",
	"SENSING_OF_XPOSITION": "o x da posição",
	"SENSING_OF_YPOSITION": "o y da posição",
	"SENSING_OF_DIRECTION": "a direcção",
	"SENSING_OF_COSTUMENUMBER": "o número do traje",
	"SENSING_OF_COSTUMENAME": "o nome do traje",
	"SENSING_OF_SIZE": "o tamanho",
	"SENSING_OF_VOLUME": "o volume",
	"SENSING_OF_BACKDROPNUMBER": "o número do cenário",
	"SENSING_OF_BACKDROPNAME": "o nome do cenário",
	"SENSING_OF_STAGE": "o palco",
	"SENSING_CURRENT": "%1 actual",
	"SENSING_CURRENT_YEAR": "o ano",
	"SENSING_CURRENT_MONTH": "o mês",
	"SENSING_CURRENT_DATE": "a data",
	"SENSING_CURRENT_DAYOFWEEK": "o dia da semana",
	"SENSING_CURRENT_HOUR": "a hora",
	"SENSING_CURRENT_MINUTE": "o minuto",
	"SENSING_CURRENT_SECOND": "o segundo",
	"SENSING_DAYSSINCE2000": "o número de dias desde 2000",
	"SENSING_USERNAME": "o nome de utilizador",
	"SENSING_USERID": "o ID de utilizador",
	"SOUND_PLAY": "toca o som %1",
	"SOUND_PLAYUNTILDONE": "toca o som %1 até terminar",
	"SOUND_STOPALLSOUNDS": "pára todos os sons",
	"SOUND_SETEFFECTO": "altera o teu efeito %1 para %2",
	"SOUND_CHANGEEFFECTBY": "adiciona ao teu efeito %1 o valor %2",
	"SOUND_CLEAREFFECTS": "cancela todos os teus efeitos sonoros",
	"SOUND_EFFECTS_PITCH": "tom",
	"SOUND_EFFECTS_PAN": "canal esquerdo/direito",
	"SOUND_CHANGEVOLUMEBY": "adiciona %1 % ao teu volume",
	"SOUND_SETVOLUMETO": "altera o teu volume para %1%",
	"SOUND_VOLUME": "o volume",
	"SOUND_RECORD": "gravar…",
	"CATEGORY_MOTION": "Movimento",
	"CATEGORY_LOOKS": "Aparência",
	"CATEGORY_SOUND": "Som",
	"CATEGORY_EVENTS": "Eventos",
	"CATEGORY_CONTROL": "Controlo",
	"CATEGORY_SENSING": "Sensores",
	"CATEGORY_OPERATORS": "Operadores",
	"CATEGORY_VARIABLES": "Variáveis",
	"CATEGORY_MYBLOCKS": "Os Meus Blocos",
	"DUPLICATE": "Duplicar",
	"DELETE": "Remover",
	"ADD_COMMENT": "Adicionar Comentário",
	"REMOVE_COMMENT": "Remover Comentário",
	"DELETE_BLOCK": "Remover Bloco",
	"DELETE_X_BLOCKS": "Remover %1 Blocos",
	"DELETE_ALL_BLOCKS": "Remover todos os %1 blocos?",
	"CLEAN_UP": "Arrumar Blocos",
	"HELP": "Ajuda",
	"UNDO": "Desfazer",
	"REDO": "Refazer",
	"EDIT_PROCEDURE": "Editar",
	"SHOW_PROCEDURE_DEFINITION": "Ir para a definição",
	"WORKSPACE_COMMENT_DEFAULT_TEXT": "Diga qualquer coisa…",
	"COLOUR_HUE_LABEL": "Matiz",
	"COLOUR_SATURATION_LABEL": "Saturação",
	"COLOUR_BRIGHTNESS_LABEL": "Brilho",
	"CHANGE_VALUE_TITLE": "Alterar o valor:",
	"RENAME_VARIABLE": "Renomear a variável",
	"RENAME_VARIABLE_TITLE": "Renomear todas as variáveis «%1» para:",
	"RENAME_VARIABLE_MODAL_TITLE": "Renomear Variável",
	"NEW_VARIABLE": "Criar uma Variável",
	"NEW_VARIABLE_TITLE": "Novo nome da variável:",
	"VARIABLE_MODAL_TITLE": "Nova Variável",
	"VARIABLE_ALREADY_EXISTS": "Já existe uma variável com o nome «%1».",
	"VARIABLE_ALREADY_EXISTS_FOR_ANOTHER_TYPE": "Já existe uma variável com o nome «%1» do tipo «%2».",
	"DELETE_VARIABLE_CONFIRMATION": "Remover %1 utilizações da variável «%2»?",
	"CANNOT_DELETE_VARIABLE_PROCEDURE": "Não é possível remover a variável «%1» porque é parte da definição da função «%2»",
	"DELETE_VARIABLE": "Remover a variável «%1»",
	"NEW_PROCEDURE": "Criar um Bloco",
	"PROCEDURE_ALREADY_EXISTS": "Já existe um procedimento com o nome «%1».",
	"PROCEDURE_DEFAULT_NAME": "nome do bloco",
	"PROCEDURE_USED": "Para remover uma definição de bloco, remova primeiro todas as utilizações desse bloco",
	"NEW_LIST": "Criar uma Lista",
	"NEW_LIST_TITLE": "Nome da nova lista:",
	"LIST_MODAL_TITLE": "Nova Lista",
	"LIST_ALREADY_EXISTS": "Já existe uma lista com o nome «%1».",
	"RENAME_LIST_TITLE": "Renomear todas as listas «%1» para:",
	"RENAME_LIST_MODAL_TITLE": "Renomear Lista",
	"DEFAULT_LIST_ITEM": "uma coisa",
	"DELETE_LIST": "Remover a lista «%1»",
	"RENAME_LIST": "Renomear a lista",
	"NEW_BROADCAST_MESSAGE": "Nova mensagem",
	"NEW_BROADCAST_MESSAGE_TITLE": "Nome da nova mensagem:",
	"BROADCAST_MODAL_TITLE": "Nova Mensagem",
	"DEFAULT_BROADCAST_MESSAGE_NAME": "Mensagem 1",
	"ROBOT_LED": "LED monocromático %1 %2",
	"ROBOT_ON": "Ligar",
	"ROBOT_OFF": "Desligar",
	"ROBOT_LED_LUMINANCE": "LED monocromático %1 definir luminosidade %2",
	"EVENT_WHENARDUINOBEGIN": "Iniciar programa",
	"ROBOT_IR_RECEIVER_MODULE": "Módulo receptor de IR %1 recebeu %2 pressionado",
	"ROBOT_ULTRASONIC_SENSOR": "Sensor ultrassônico (cm) Pino Trig %1 Pino Echo %2",
	"ROBOT_HUMIDITY_TEMPERATURE": "Umidade temperatura %1 valor %2",
	"ROBOT_TEMPERATURE": "Temperatura",
	"ROBOT_HUMIDITY": "Umidade",
	"ROBOT_DC_MOTOR": "Motor DC 130 IN-%1 IN+%2 velocidade %3",
	"ROBOT_BUTTON_MODULE": "Botão %1 pressionado",
	"ROBOT_PHOTORESISTOR_SENSOR": "Sensor de luz %1",
	"ROBOT_SOUND_SENSOR": "Sensor de som %1",
	"ROBOT_PIR_MOTION_SENSOR": "Sensor de movimento PIR %1",
	"ROBOT_MOISTURE_SENSOR": "Sensor de umidade %1",
	"ROBOT_RAINDROP_SENSOR": "Sensor de gotas de chuva %1",
	"ROBOT_SG90_MODULE": "Servo motor %1 definir ângulo para %2",
	"ROBOT_LASER_MODULE": "Laser %1 %2",
	"ROBOT_P_BUZZER": "Buzzer Pino %1 frequência %2 duração %3 batidas",
	"ROBOT_HALF": "Meio",
	"ROBOT_QUARTER": "Um quarto",
	"ROBOT_ONE_EIGHTH": "Um oitavo",
	"ROBOT_WHOLE_BEAT": "Inteiro",
	"ROBOT_DOUBLE_BEAT": "Duplo",
	"ROBOT_MQ4_GAS_SENSOR": "Sensor de gás MQ-4 %1",
	"ROBOT_TRACE_SENSOR_SET": "Configurar pinos do sensor de rastreamento de linha (R: %1, M: %2, L: %3)",
	"ROBOT_TRACE_SENSOR_GET": "Obter valor do sensor de rastreamento %1",
	"ROBOT_POTENTIOMETER": "Potenciômetro %1",
	"ROBOT_TOUCH_SENSOR": "Sensor táctil %1 foi tocado",
	"ROBOT_FLAME_SENSOR": "Sensor de chama %1",
	"ROBOT_RGB_MODULE": "Luz RGB %1 Vermelho %2 %3 Verde %4 %5 Azul %6",
	"ROBOT_SET_TAPE_LIGHTS": "Luzes de fita %1 %2 %3",
	"ROBOT_TAPE_LIGHTS": "Luzes de fita %1 %2 Vermelho %3 Verde %4 Azul %5",
	"ROBOT_HUMIDIFIER": "Umidificador %1 %2",
	"ROBOT_WATER_SENSOR": "Sensor de água %1",
	"ROBOT_DIGIT_TUBE_DISPLAY_NUMBER": "Módulo de display de tubo de dígitos mostra número %1",
	"ROBOT_DIGIT_TUBE_DISPLAY_STRING": "Módulo de display de tubo de dígitos mostra string %1",
	"ROBOT_DIGIT_TUBE_DISPLAY_NUMBER_PIN": "Módulo de display de tubo de dígitos CLK %1 DIO %2 mostra número %3",
	"ROBOT_DIGIT_TUBE_DISPLAY_STRING_PIN": "Módulo de display de tubo de dígitos CLK %1 DIO %2 mostra string %3",
	"ROBOT_COLOR_SENSOR_LIGHT": "Sensor de cor %1 luz %2",
	"ROBOT_COLOR_SENSOR_COLORS": "Sensor de cor %1",
	"ROBOT_BEIGHTNESS": "Luminosidade",
	"ROBOT_RED": "Vermelho",
	"ROBOT_GREEN": "Verde",
	"ROBOT_BLUE": "Azul",
	"ROBOT_RFID": "Ler ID RFID",
	"ROBOT_LCD_STRING": "LCD x%1y%2 mostra caractere %3",
	"ROBOT_LCD_NUMBER": "LCD x%1y%2 mostra número %3",
	"ROBOT_LCD_CLEAR": "Limpar tela LCD",
	"ROBOT_LCD_MODEL": "Modo de rolagem LCD %1 %2 Rolagem mostra caractere %3 a cada %4 segundos",
	"ROBOT_FIRST_ROW": "Primeira linha",
	"ROBOT_SENCOND_ROW": "Segunda linha",
	"ROBOT_ALEFT": "Para a esquerda",
	"ROBOT_RIGHT": "Para a direita",
	"ROBOT_LCD_FLASH": "Modo de piscar LCD %1",
	"ROBOT_ON_THE_BACKLIGHT": "Ligar luz de fundo",
	"ROBOT_OFF_THE_BACKLIGHT": "Desligar luz de fundo",
	"ROBOT_BLDC": "Motor DC %1 velocidade %2",
	"ROBOT_MP3": "MP3 RX %1 TX %2 %3",
	"ROBOT_PLAY": "Continuar reprodução",
	"ROBOT_PAUSE": "Pausar reprodução",
	"ROBOT_PREVIOUS": "Faixa anterior",
	"ROBOT_NEXT": "Próxima faixa",
	"ROBOT_MP3_MODULE_PLAY": "MP3 RX %1 TX %2 reproduzir faixa %3",
	"ROBOT_MP3_MODULE_VOLUME": "MP3 RX %1 TX %2 definir volume para %3",
	"ROBOT_MP3_MODULE_PLAY_OVER": "MP3 RX %1 TX %2 parar reprodução",
	"ROBOT_VOICE_RECOGNITION": "Obter o valor da instrução do módulo de reconhecimento de voz RX%1TX%2",
	"ROBOT_OPEN_THE_DOOR": "Abrir porta",
	"ROBOT_CLOSE_THE_DOOR": "Fechar porta",
	"ROBOT_OPEN_THE_WINDOW": "Abrir janela",
	"ROBOT_CLOSE_THE_WINDOW": "Fechar janela",
	"ROBOT_OPEN_THE_BEE": "Iniciar abelha",
	"ROBOT_CLOSE_THE_BEE": "Parar abelha",
	"ROBOT_OPEN_THE_LIGHT": "Ligar luz LED",
	"ROBOT_CLOSE_THE_LIGHT": "Desligar luz LED",
	"ROBOT_OPEN_THE_LASER": "Ligar laser",
	"ROBOT_CLOSE_THE_LASER": "Desligar laser",
	"ROBOT_OPEN_THE_COLOR_LIGHT": "Ligar luz colorida padrão",
	"ROBOT_CLOSE_THE_COLOR_LIGHT": "Desligar luz colorida padrão",
	"ROBOT_RELAY_MODULE": "Relé %1 %2",
	"ROBOT_OLED_SET": "OLED definir tamanho da fonte %1",
	"ROBOT_OLED_STRING": "Exibir caractere %3 na tela OLED na posição x%1y%2",
	"ROBOT_OLED_NUMBER": "Exibir número %3 na tela OLED na posição x%1y%2",
	"ROBOT_OLED_CLEAR": "Limpar buffer OLED",
	"ROBOT_PRINT": "Serial %1 imprimir %2",
	"CATEGORY_ROBOTS": "Robôs",
	"ROBOT_WIFI_AP": "Ativar modo AP, SSID: %1, Senha: %2, Canal: %3",
	"ROBOT_CLOSE_AP": "Desativar modo AP",
	"ROBOT_WIFI": "Conectar ao WiFi, SSID: %1, Senha: %2",
	"ROBOT_WIFI_INFO": "Informações do WiFi: %1",
	"ROBOT_WIFI_INIT_SERVER": "Inicializar servidor",
	"ROBOT_WIFI_RUN_SERVER": "Executar servidor",
	"ROBOT_WIFI_CLIENT": "Verificar se o cliente WiFi existe",
	"ROBOT_WIFI_CLIENT_GET": "Receber dados do cliente WiFi",
	"ROBOT_WIFI_CLIENT_SENT": "Enviar dados para o cliente WiFi: %1",
	"ROBOT_WIFI_CLOSE_CLIENT": "Fechar o cliente WiFi",
	"ROBOT_WIFI_CLIENT_CONNECT": "Verificar se o cliente WiFi está conectado",
	"ROBOT_WIFI_CLIENT_DISPLAY": "Verificar se o cliente WiFi está disponível",
	"ROBOT_WIFI_CLOSE": "Desconectar do WiFi",
	"ROBOT_WIFI_CONNECT_INFO": "Informações de conexão",
	"ROBOT_WIFI_CONNECT_IP": "Endereço IP",
	"ROBOT_VIBRATION": "Sensor de vibração %1",
	"ROBOT_BLUE_TOOTH_INIT": "Inicializar Bluetooth %1",
	"ROBOT_BLUE_TOOTH_GET": "Receber dados do Bluetooth",
	"ROBOT_BLUE_TOOTH_SEND": "Enviar dados via Bluetooth: %1",
	"ROBOT_BLUE_TOOTH_GET_MAC": "Obter endereço MAC do Bluetooth",
	"ROBOT_BLUE_TOOTH_CLOSE": "Desconectar Bluetooth",
	"ROBOT_GET_KEY_BOARD": "Obter teclado de matriz, Linhas: %1%2%3%4, Colunas: %5%6%7%8",
	"Blockly.Msg.SET.DATA.TYPE": "Definir tipo de dados %1 %2",
	"ROBOT.FLOAT": "Número flutuante",
	"ROBOT.INT": "Número inteiro",
	"SET_DATA_TYPE": "Definir tipo de dados %1 %2",
	"ROBOT_FLOAT": "Número de ponto flutuante",
	"ROBOT_INT": "Número inteiro",
	"OPERATOR_GETSTRING": "Obter os caracteres %2 a %3 de %1",
	"OPERATOR_LOCATION": "Obter a posição de %1 em %2",
	"OPERATOR_CR": "Retorno de Carro",
	"OPERATOR_BR": "Quebra de Linha",
	"OPERATOR_CR_BR": "Retorno de Carro e Quebra de Linha",
	"ROBOT_VOICE_RECOGNITION_INIT": "Inicializando o módulo de reconhecimento de voz RX%1TX%2",
	"ROBOT_GET_TIME": "Obter hora",
	"ROBOT_GET_TOUCH_BOARD": "Obter posição do teclado táctil",
	"STRIN_TO_INT": "Converter %1 em inteiro",
	"ROBOT_GET_CITY_CODE": "Código da cidade atual",
	"ROBOT_REFRESH_WRATHER": "Atualizar clima %1",
	"ROBOT_GET_WEATHER_INFO": "Obter %1",
	"ROBOT_CITY_NAME": "Nome da cidade em inglês",
	"ROBOT_DIRECTION": "Direção do vento",
	"ROBOT_SPEED": "Velocidade do vento",
	"ROBOT_TEMP": "Temperatura",
	"ROBOT_weather": "Clima",
	"ROBOT_PM": "Valor de PM",
	"ROBOT_NTP_INIT": "Inicializar servidor NTP",
	"ROBOT_UPDATE_TIME": "Atualizar hora",
	"ROBOT_GET_TIME_INFO": "Obter hora %1",
	"ROBOT_HOUR": "Hora",
	"ROBOT_MINUTE": "Minuto",
	"ROBOT_SECODE": "Segundo",
	"ROBOT_WEEK": "Dia da semana",
	"ROBOT_TRAFFIC_LIGHT": "Semáforo Verde%1%2 Amarelo%3%4 Vermelho%5%6",
	"ROBOT_INFRARA_PROXIMITY": "Módulo de sensor de proximidade infravermelho %1 detectou obstáculo",
	"ROBOT_OLED_SHOW": "Exibir tela OLED",
	"ROBOT_OLED_INIT": "Inicializar OLED",
	"ROBOT_GET_WEATHER_DATA": "Obter dados meteorológicos %1",
	"CATEGORY_ROBOTS_RGB": "Fita de luzes RGB",
	"CATEGORY_ROBOTS_Digit_Tube": "Display de 4 dígitos",
	"CATEGORY_ROBOTS_LCD": "Módulo LCD",
	"CATEGORY_ROBOTS_MP3": "Módulo MP3",
	"CATEGORY_ROBOTS_Voice_Recognition": "Reconhecimento de voz",
	"CATEGORY_ROBOTS_OLED": "Módulo OLED",
	"CATEGORY_ROBOTS_DIGIT": "Display de 4 dígitos",
	"CATEGORY_ROBOTS_VOICE": "Reconhecimento de voz",
	"CATEGORY_ROBOTS_WIFI": "Módulo WIFI",
	"CATEGORY_ROBOTS_BLUETOOTH": "Módulo Bluetooth",
	"CATEGORY_ROBOTS_WRATHER": "Módulo de clima",
	"CATEGORY_ROBOTS_ITS": "Sistema de transporte inteligente",
	"ROBOT_INIT_WEB_SERVER": "Inicializar porta do servidor web %1",
	"ROBOT_WEB_DISPOSE_DATA": "servidor web processa o pedido %1",
	"ROBOT_SEND_DATA_TO_WEB": "servidor web envia dados %1 para o cliente %2",
	"ROBOT_TEXT": "Texto",
	"ROBOT_WEBPAGE": "Página web",
	"ROBOT_GET_WEB_DATA": "receber valor do cliente %1",
	"ROBOT_STRING": "String %1",
	"ROBOT_BREAK": "Interromper loop atual",
	"ROBOT_ASYNC_DELAY": "atraso assíncrono %1"
}